pwnchk/__init__.py
pwnchk/pwnchk.py
pwnchk/py.typed
pwnchk-0.0.1.dist-info/METADATA
pwnchk-0.0.1.dist-info/WHEEL
pwnchk-0.0.1.dist-info/entry_points.txt
pwnchk-0.0.1.dist-info/top_level.txt
pwnchk-0.0.1.dist-info/RECORD
